mannetroll_palinstrophy-0.1.2.dist-info/licenses/LICENSE
palinstrophy/__init__.py
palinstrophy/palinstrophy.icns
palinstrophy/palinstrophy.ico
palinstrophy/turbo_main.py
palinstrophy/turbo_simulator.py
palinstrophy/turbo_wrapper.py
mannetroll_palinstrophy-0.1.2.dist-info/METADATA
mannetroll_palinstrophy-0.1.2.dist-info/WHEEL
mannetroll_palinstrophy-0.1.2.dist-info/entry_points.txt
mannetroll_palinstrophy-0.1.2.dist-info/top_level.txt
mannetroll_palinstrophy-0.1.2.dist-info/RECORD
