Metadata-Version: 2.4
Name: mannetroll-palinstrophy
Version: 0.1.2
Summary: 2D Turbulence (SciPy + CuPy)
Author: Torbjörn Sjögren
License-Expression: MIT
Requires-Python: <3.14,>=3.13
License-File: LICENSE
Requires-Dist: numpy<3,>=2.3.5
Requires-Dist: numba<1,>=0.63.1
Requires-Dist: Pillow<13,>=12
Requires-Dist: scipy<2,>=1.16.3
Requires-Dist: PySide6<7,>=6.10.1
Requires-Dist: matplotlib<4,>=3.10.8
Provides-Extra: cuda
Requires-Dist: cupy-cuda13x>=13.6.0; sys_platform != "darwin" and extra == "cuda"
Requires-Dist: fastrlock>=0.8; extra == "cuda"
Dynamic: license-file
